text.py
abram_text_tools-1.1.0.dist-info/METADATA
abram_text_tools-1.1.0.dist-info/WHEEL
abram_text_tools-1.1.0.dist-info/top_level.txt
abram_text_tools-1.1.0.dist-info/RECORD
